[{"total":11,"weeks":[{"w":1698537600,"a":2617,"d":508,"c":8},{"w":1699142400,"a":262,"d":2,"c":2},{"w":1699747200,"a":0,"d":0,"c":0},{"w":1700352000,"a":0,"d":0,"c":0},{"w":1700956800,"a":0,"d":0,"c":0},{"w":1701561600,"a":0,"d":0,"c":0},{"w":1702166400,"a":0,"d":0,"c":0},{"w":1702771200,"a":0,"d":0,"c":0},{"w":1703376000,"a":0,"d":0,"c":0},{"w":1703980800,"a":0,"d":0,"c":0},{"w":1704585600,"a":0,"d":0,"c":0},{"w":1705190400,"a":708,"d":617,"c":1},{"w":1705795200,"a":0,"d":0,"c":0},{"w":1706400000,"a":0,"d":0,"c":0},{"w":1707004800,"a":0,"d":0,"c":0},{"w":1707609600,"a":0,"d":0,"c":0},{"w":1708214400,"a":0,"d":0,"c":0},{"w":1708819200,"a":0,"d":0,"c":0},{"w":1709424000,"a":0,"d":0,"c":0},{"w":1710028800,"a":0,"d":0,"c":0},{"w":1710633600,"a":0,"d":0,"c":0},{"w":1711238400,"a":0,"d":0,"c":0},{"w":1711843200,"a":0,"d":0,"c":0},{"w":1712448000,"a":0,"d":0,"c":0},{"w":1713052800,"a":0,"d":0,"c":0}],"author":{"login":"sgued","id":51865119,"node_id":"MDQ6VXNlcjUxODY1MTE5","avatar_url":"https://avatars.githubusercontent.com/u/51865119?v=4","gravatar_id":"","url":"https://api.github.com/users/sgued","html_url":"https://github.com/sgued","followers_url":"https://api.github.com/users/sgued/followers","following_url":"https://api.github.com/users/sgued/following{/other_user}","gists_url":"https://api.github.com/users/sgued/gists{/gist_id}","starred_url":"https://api.github.com/users/sgued/starred{/owner}{/repo}","subscriptions_url":"https://api.github.com/users/sgued/subscriptions","organizations_url":"https://api.github.com/users/sgued/orgs","repos_url":"https://api.github.com/users/sgued/repos","events_url":"https://api.github.com/users/sgued/events{/privacy}","received_events_url":"https://api.github.com/users/sgued/received_events","type":"User","site_admin":false}}]